{
  "_id": "6643cbe9-4480-4221-b168-60870c5a5f37",
  "name": "LHS Autogenerated 20",
  "run_start_time": "2018-05-25T14:17:33.638Z",
  "run_end_time": "2018-05-25T14:19:03.060Z",
  "status": "completed",
  "status_message": "completed normal",
  "ambient_loop_temperature_setpoint.design_delta": 3.0242438709735873,
  "ambient_loop_temperature_setpoint.setpoint_temperature": 19.833552009030246,
  "internal_loads_multiplier.epd_multiplier": 2.524152777348482,
  "internal_loads_multiplier.lpd_multiplier": 2.9458250616853823,
  "openstudio_results.annual_peak_electric_demand": 32.80927,
  "openstudio_results.district_cooling_ip": 236.00448202023452,
  "openstudio_results.district_heating_ip": 0.04284474104166787,
  "openstudio_results.electricity_ip": 116981.02614933888,
  "openstudio_results.eui": 115.4487077433756,
  "openstudio_results.total_site_eui": 115.4487077433756,
  "openstudio_results.unmet_hours_during_occupied_cooling": 83.0,
  "openstudio_results.unmet_hours_during_occupied_heating": 0.0,
  "data_point_uuid": "/data_points/6643cbe9-4480-4221-b168-60870c5a5f37"
}