{
  "_id": "b9525a4d-de50-4e70-941a-30c1b8ce8957",
  "name": "LHS Autogenerated 39",
  "run_start_time": "2018-05-25T14:25:44.658Z",
  "run_end_time": "2018-05-25T14:28:05.711Z",
  "status": "completed",
  "status_message": "completed normal",
  "ambient_loop_temperature_setpoint.design_delta": 2.3492009171284733,
  "ambient_loop_temperature_setpoint.setpoint_temperature": 16.714736855449154,
  "internal_loads_multiplier.epd_multiplier": 1.7009563295784407,
  "internal_loads_multiplier.lpd_multiplier": 1.9119815776370466,
  "openstudio_results.annual_peak_electric_demand": 22.82648,
  "openstudio_results.district_cooling_ip": 159.6502020075207,
  "openstudio_results.district_heating_ip": 0.20887609871339477,
  "openstudio_results.electricity_ip": 79661.4438061722,
  "openstudio_results.eui": 78.45647356627023,
  "openstudio_results.total_site_eui": 78.45647356627023,
  "openstudio_results.unmet_hours_during_occupied_cooling": 52.0,
  "openstudio_results.unmet_hours_during_occupied_heating": 0.0,
  "data_point_uuid": "/data_points/b9525a4d-de50-4e70-941a-30c1b8ce8957"
}