{
  "_id": "42efa1f5-3082-4b56-a35e-d082b287678b",
  "name": "LHS Autogenerated 51",
  "run_start_time": "2018-08-22T16:03:45.357Z",
  "run_end_time": "2018-08-22T16:04:54.697Z",
  "status": "completed",
  "status_message": "completed normal",
  "ambient_loop_temperature_setpoint.design_delta": 6.438599127009511,
  "ambient_loop_temperature_setpoint.setpoint_temperature": 22.569539291993713,
  "internal_loads_multiplier.lpd_multiplier": 2.7448173516909358,
  "openstudio_results.annual_peak_electric_demand": 23.268130000000003,
  "openstudio_results.district_cooling_ip": 85.84917544893493,
  "openstudio_results.district_heating_ip": 3.942416938232102,
  "openstudio_results.electricity_ip": 76670.44909721111,
  "openstudio_results.eui": 63.86733175543361,
  "openstudio_results.total_site_eui": 63.86733175543361,
  "openstudio_results.unmet_hours_during_occupied_cooling": 0.0,
  "openstudio_results.unmet_hours_during_occupied_heating": 1.0,
  "data_point_uuid": "/data_points/42efa1f5-3082-4b56-a35e-d082b287678b"
}